[
  {
    "id": 1,
    "name": "Central Park Diner",
    "city": "New York",
    "address": "123 Central Park West",
    "cuisine": "American",
    "seatingCapacity": 80,
    "availableCapacity": 20,
    "availableReservations": ["12:00 PM", "2:00 PM", "7:00 PM"],
    "mood": "casual"
  },
  {
    "id": 2,
    "name": "Empire Steakhouse",
    "city": "New York",
    "address": "200 Broadway, New York, NY",
    "cuisine": "Steakhouse",
    "seatingCapacity": 120,
    "availableCapacity": 45,
    "availableReservations": ["6:00 PM", "8:00 PM", "9:30 PM"],
    "mood": "sophisticated"
  },
  {
    "id": 3,
    "name": "Little Italy Bistro",
    "city": "New York",
    "address": "45 Mulberry Street",
    "cuisine": "Italian",
    "seatingCapacity": 60,
    "availableCapacity": 10,
    "availableReservations": ["1:00 PM", "7:30 PM", "9:00 PM"],
    "mood": "romantic"
  },
  {
    "id": 4,
    "name": "Brooklyn Vegan",
    "city": "New York",
    "address": "250 Bedford Ave",
    "cuisine": "Vegan",
    "seatingCapacity": 50,
    "availableCapacity": 15,
    "availableReservations": ["12:30 PM", "6:30 PM", "8:00 PM"],
    "mood": "casual"
  },
  {
    "id": 5,
    "name": "Manhattan Sushi",
    "city": "New York",
    "address": "10 East 34th St",
    "cuisine": "Japanese",
    "seatingCapacity": 70,
    "availableCapacity": 25,
    "availableReservations": ["5:30 PM", "7:00 PM", "9:15 PM"],
    "mood": "cozy"
  },
  {
    "id": 6,
    "name": "Sunset Grill",
    "city": "Los Angeles",
    "address": "101 Sunset Blvd",
    "cuisine": "American",
    "seatingCapacity": 90,
    "availableCapacity": 30,
    "availableReservations": ["11:00 AM", "1:00 PM", "7:00 PM"],
    "mood": "vibrant"
  },
  {
    "id": 7,
    "name": "Beverly Hills Bistro",
    "city": "Los Angeles",
    "address": "500 Rodeo Drive",
    "cuisine": "French",
    "seatingCapacity": 100,
    "availableCapacity": 40,
    "availableReservations": ["12:00 PM", "6:00 PM", "8:00 PM"],
    "mood": "elegant"
  },
  {
    "id": 8,
    "name": "Hollywood Vegan",
    "city": "Los Angeles",
    "address": "220 Hollywood Blvd",
    "cuisine": "Vegan",
    "seatingCapacity": 60,
    "availableCapacity": 20,
    "availableReservations": ["1:00 PM", "7:30 PM", "9:00 PM"],
    "mood": "casual"
  },
  {
    "id": 9,
    "name": "LA Tacos",
    "city": "Los Angeles",
    "address": "300 Mission Rd",
    "cuisine": "Mexican",
    "seatingCapacity": 80,
    "availableCapacity": 35,
    "availableReservations": ["12:00 PM", "2:00 PM", "8:00 PM"],
    "mood": "lively"
  },
  {
    "id": 10,
    "name": "Ocean View Seafood",
    "city": "Los Angeles",
    "address": "400 Pacific Coast Hwy",
    "cuisine": "Seafood",
    "seatingCapacity": 110,
    "availableCapacity": 50,
    "availableReservations": ["6:30 PM", "8:30 PM", "10:00 PM"],
    "mood": "romantic"
  },
  {
    "id": 11,
    "name": "Windy City Grill",
    "city": "Chicago",
    "address": "55 Michigan Ave",
    "cuisine": "American",
    "seatingCapacity": 100,
    "availableCapacity": 45,
    "availableReservations": ["12:00 PM", "6:00 PM", "9:00 PM"],
    "mood": "casual"
  },
  {
    "id": 12,
    "name": "Deep Dish Delight",
    "city": "Chicago",
    "address": "70 Pizza Lane",
    "cuisine": "Italian",
    "seatingCapacity": 80,
    "availableCapacity": 25,
    "availableReservations": ["11:30 AM", "1:30 PM", "7:30 PM"],
    "mood": "family-friendly"
  },
  {
    "id": 13,
    "name": "Chicago Steakhouse",
    "city": "Chicago",
    "address": "88 Wacker Drive",
    "cuisine": "Steakhouse",
    "seatingCapacity": 120,
    "availableCapacity": 55,
    "availableReservations": ["6:00 PM", "8:00 PM", "9:30 PM"],
    "mood": "sophisticated"
  },
  {
    "id": 14,
    "name": "River North Noodles",
    "city": "Chicago",
    "address": "15 River North Plaza",
    "cuisine": "Asian Fusion",
    "seatingCapacity": 70,
    "availableCapacity": 30,
    "availableReservations": ["12:00 PM", "2:00 PM", "7:00 PM"],
    "mood": "modern"
  },
  {
    "id": 15,
    "name": "Millennium Vegan",
    "city": "Chicago",
    "address": "99 Millennium Park",
    "cuisine": "Vegan",
    "seatingCapacity": 60,
    "availableCapacity": 20,
    "availableReservations": ["12:30 PM", "6:30 PM", "8:30 PM"],
    "mood": "eco-friendly"
  },
  {
    "id": 16,
    "name": "Space City BBQ",
    "city": "Houston",
    "address": "101 NASA Blvd",
    "cuisine": "BBQ",
    "seatingCapacity": 150,
    "availableCapacity": 60,
    "availableReservations": ["1:00 PM", "7:00 PM", "9:00 PM"],
    "mood": "rustic"
  },
  {
    "id": 17,
    "name": "Houston Hot Wings",
    "city": "Houston",
    "address": "202 Main St",
    "cuisine": "American",
    "seatingCapacity": 90,
    "availableCapacity": 35,
    "availableReservations": ["12:00 PM", "6:30 PM", "8:00 PM"],
    "mood": "casual"
  },
  {
    "id": 18,
    "name": "Tex-Mex Fiesta",
    "city": "Houston",
    "address": "303 Fiesta Ln",
    "cuisine": "Tex-Mex",
    "seatingCapacity": 110,
    "availableCapacity": 40,
    "availableReservations": ["12:00 PM", "7:00 PM", "9:30 PM"],
    "mood": "lively"
  },
  {
    "id": 19,
    "name": "Bayou Bistro",
    "city": "Houston",
    "address": "404 Bayou Rd",
    "cuisine": "Cajun",
    "seatingCapacity": 80,
    "availableCapacity": 25,
    "availableReservations": ["1:30 PM", "6:00 PM", "8:00 PM"],
    "mood": "vibrant"
  },
  {
    "id": 20,
    "name": "Downtown Dim Sum",
    "city": "Houston",
    "address": "505 Central Ave",
    "cuisine": "Chinese",
    "seatingCapacity": 70,
    "availableCapacity": 15,
    "availableReservations": ["12:00 PM", "2:00 PM", "7:00 PM"],
    "mood": "modern"
  },
  {
    "id": 21,
    "name": "Desert Oasis",
    "city": "Phoenix",
    "address": "101 Desert Rd",
    "cuisine": "Mediterranean",
    "seatingCapacity": 90,
    "availableCapacity": 30,
    "availableReservations": ["12:00 PM", "7:00 PM", "9:00 PM"],
    "mood": "romantic"
  },
  {
    "id": 22,
    "name": "Cactus Cafe",
    "city": "Phoenix",
    "address": "202 Cactus Blvd",
    "cuisine": "American",
    "seatingCapacity": 70,
    "availableCapacity": 20,
    "availableReservations": ["11:30 AM", "1:30 PM", "6:30 PM"],
    "mood": "casual"
  },
  {
    "id": 23,
    "name": "Phoenix Pizzeria",
    "city": "Phoenix",
    "address": "303 Pizza St",
    "cuisine": "Italian",
    "seatingCapacity": 80,
    "availableCapacity": 35,
    "availableReservations": ["12:00 PM", "7:30 PM", "9:00 PM"],
    "mood": "family-friendly"
  },
  {
    "id": 24,
    "name": "Sunrise Sushi",
    "city": "Phoenix",
    "address": "404 Sunrise Ave",
    "cuisine": "Japanese",
    "seatingCapacity": 60,
    "availableCapacity": 15,
    "availableReservations": ["5:30 PM", "7:00 PM", "8:30 PM"],
    "mood": "cozy"
  },
  {
    "id": 25,
    "name": "Valley Vegan",
    "city": "Phoenix",
    "address": "505 Valley Dr",
    "cuisine": "Vegan",
    "seatingCapacity": 50,
    "availableCapacity": 10,
    "availableReservations": ["12:30 PM", "6:00 PM", "8:00 PM"],
    "mood": "eco-friendly"
  },
  {
    "id": 26,
    "name": "Liberty Bell Diner",
    "city": "Philadelphia",
    "address": "100 Independence Ave",
    "cuisine": "American",
    "seatingCapacity": 100,
    "availableCapacity": 45,
    "availableReservations": ["12:00 PM", "6:00 PM", "9:00 PM"],
    "mood": "historic"
  },
  {
    "id": 27,
    "name": "Philly Cheesesteak House",
    "city": "Philadelphia",
    "address": "200 Market St",
    "cuisine": "American",
    "seatingCapacity": 80,
    "availableCapacity": 30,
    "availableReservations": ["12:30 PM", "7:00 PM", "9:30 PM"],
    "mood": "casual"
  },
  {
    "id": 28,
    "name": "Old City Bistro",
    "city": "Philadelphia",
    "address": "300 Old City Rd",
    "cuisine": "European",
    "seatingCapacity": 70,
    "availableCapacity": 25,
    "availableReservations": ["1:00 PM", "6:30 PM", "8:30 PM"],
    "mood": "romantic"
  },
  {
    "id": 29,
    "name": "Rittenhouse Italian",
    "city": "Philadelphia",
    "address": "400 Rittenhouse Square",
    "cuisine": "Italian",
    "seatingCapacity": 90,
    "availableCapacity": 40,
    "availableReservations": ["12:00 PM", "7:00 PM", "9:00 PM"],
    "mood": "sophisticated"
  },
  {
    "id": 30,
    "name": "Franklin's Fusion",
    "city": "Philadelphia",
    "address": "500 Franklin St",
    "cuisine": "Fusion",
    "seatingCapacity": 75,
    "availableCapacity": 35,
    "availableReservations": ["12:00 PM", "6:00 PM", "8:00 PM"],
    "mood": "modern"
  },
  {
    "id": 31,
    "name": "Alamo Cafe",
    "city": "San Antonio",
    "address": "101 Alamo Plaza",
    "cuisine": "Tex-Mex",
    "seatingCapacity": 90,
    "availableCapacity": 30,
    "availableReservations": ["12:00 PM", "7:00 PM", "9:00 PM"],
    "mood": "historic"
  },
  {
    "id": 32,
    "name": "Riverwalk Grill",
    "city": "San Antonio",
    "address": "202 Riverwalk Blvd",
    "cuisine": "American",
    "seatingCapacity": 80,
    "availableCapacity": 25,
    "availableReservations": ["12:30 PM", "7:30 PM", "9:30 PM"],
    "mood": "romantic"
  },
  {
    "id": 33,
    "name": "Mission Modern",
    "city": "San Antonio",
    "address": "303 Mission St",
    "cuisine": "Fusion",
    "seatingCapacity": 70,
    "availableCapacity": 20,
    "availableReservations": ["1:00 PM", "6:30 PM", "8:00 PM"],
    "mood": "modern"
  },
  {
    "id": 34,
    "name": "Fiesta Flavors",
    "city": "San Antonio",
    "address": "404 Fiesta Ave",
    "cuisine": "Mexican",
    "seatingCapacity": 85,
    "availableCapacity": 35,
    "availableReservations": ["12:00 PM", "7:00 PM", "9:00 PM"],
    "mood": "vibrant"
  },
  {
    "id": 35,
    "name": "Cultural Cuisine",
    "city": "San Antonio",
    "address": "505 Heritage Dr",
    "cuisine": "International",
    "seatingCapacity": 65,
    "availableCapacity": 20,
    "availableReservations": ["12:30 PM", "6:30 PM", "8:30 PM"],
    "mood": "cosmopolitan"
  },
  {
    "id": 36,
    "name": "Beachside Bites",
    "city": "San Diego",
    "address": "101 Oceanfront",
    "cuisine": "Seafood",
    "seatingCapacity": 100,
    "availableCapacity": 50,
    "availableReservations": ["12:00 PM", "6:00 PM", "8:00 PM"],
    "mood": "relaxed"
  },
  {
    "id": 37,
    "name": "Downtown Delights",
    "city": "San Diego",
    "address": "202 Downtown St",
    "cuisine": "American",
    "seatingCapacity": 80,
    "availableCapacity": 40,
    "availableReservations": ["12:30 PM", "7:30 PM", "9:00 PM"],
    "mood": "modern"
  },
  {
    "id": 38,
    "name": "Gaslamp Gourmet",
    "city": "San Diego",
    "address": "303 Gaslamp Ave",
    "cuisine": "Mediterranean",
    "seatingCapacity": 90,
    "availableCapacity": 35,
    "availableReservations": ["1:00 PM", "7:00 PM", "9:00 PM"],
    "mood": "chic"
  },
  {
    "id": 39,
    "name": "Little Italy San Diego",
    "city": "San Diego",
    "address": "404 Little Italy St",
    "cuisine": "Italian",
    "seatingCapacity": 70,
    "availableCapacity": 30,
    "availableReservations": ["12:00 PM", "6:30 PM", "8:00 PM"],
    "mood": "romantic"
  },
  {
    "id": 40,
    "name": "Vegan Vibes",
    "city": "San Diego",
    "address": "505 Green Way",
    "cuisine": "Vegan",
    "seatingCapacity": 60,
    "availableCapacity": 15,
    "availableReservations": ["11:30 AM", "1:30 PM", "7:00 PM"],
    "mood": "eco-friendly"
  },
  {
    "id": 41,
    "name": "Lone Star Steakhouse",
    "city": "Dallas",
    "address": "101 Cowboy Rd",
    "cuisine": "Steakhouse",
    "seatingCapacity": 130,
    "availableCapacity": 60,
    "availableReservations": ["6:00 PM", "8:00 PM", "9:30 PM"],
    "mood": "rustic"
  },
  {
    "id": 42,
    "name": "Dallas BBQ",
    "city": "Dallas",
    "address": "202 BBQ Lane",
    "cuisine": "BBQ",
    "seatingCapacity": 120,
    "availableCapacity": 50,
    "availableReservations": ["12:00 PM", "7:00 PM", "9:00 PM"],
    "mood": "lively"
  },
  {
    "id": 43,
    "name": "Metro Mediterranean",
    "city": "Dallas",
    "address": "303 Urban St",
    "cuisine": "Mediterranean",
    "seatingCapacity": 100,
    "availableCapacity": 45,
    "availableReservations": ["12:00 PM", "6:30 PM", "8:30 PM"],
    "mood": "chic"
  },
  {
    "id": 44,
    "name": "Southern Comfort",
    "city": "Dallas",
    "address": "404 Southern Rd",
    "cuisine": "Southern",
    "seatingCapacity": 90,
    "availableCapacity": 40,
    "availableReservations": ["12:30 PM", "7:30 PM", "9:00 PM"],
    "mood": "cozy"
  },
  {
    "id": 45,
    "name": "Uptown Urban",
    "city": "Dallas",
    "address": "505 Uptown Blvd",
    "cuisine": "Fusion",
    "seatingCapacity": 80,
    "availableCapacity": 35,
    "availableReservations": ["1:00 PM", "6:00 PM", "8:00 PM"],
    "mood": "modern"
  },
  {
    "id": 46,
    "name": "Silicon Valley Eats",
    "city": "San Jose",
    "address": "101 Tech Park",
    "cuisine": "International",
    "seatingCapacity": 110,
    "availableCapacity": 45,
    "availableReservations": ["12:00 PM", "6:00 PM", "8:00 PM"],
    "mood": "innovative"
  },
  {
    "id": 47,
    "name": "Downtown Deli",
    "city": "San Jose",
    "address": "202 Market St",
    "cuisine": "Deli",
    "seatingCapacity": 70,
    "availableCapacity": 20,
    "availableReservations": ["11:30 AM", "1:30 PM", "7:30 PM"],
    "mood": "casual"
  },
  {
    "id": 48,
    "name": "Bay Area Bistro",
    "city": "San Jose",
    "address": "303 Bay St",
    "cuisine": "Seafood",
    "seatingCapacity": 100,
    "availableCapacity": 40,
    "availableReservations": ["12:00 PM", "7:00 PM", "9:00 PM"],
    "mood": "romantic"
  },
  {
    "id": 49,
    "name": "Techie Tacos",
    "city": "San Jose",
    "address": "404 Silicon Ave",
    "cuisine": "Mexican",
    "seatingCapacity": 90,
    "availableCapacity": 35,
    "availableReservations": ["12:00 PM", "6:30 PM", "8:30 PM"],
    "mood": "vibrant"
  },
  {
    "id": 50,
    "name": "Garden Gourmet",
    "city": "San Jose",
    "address": "505 Garden Rd",
    "cuisine": "Vegetarian",
    "seatingCapacity": 60,
    "availableCapacity": 15,
    "availableReservations": ["12:30 PM", "7:00 PM", "9:00 PM"],
    "mood": "eco-friendly"
  }
]
